aiofauna_llm/__init__.py
aiofauna_llm/schemas/__init__.py
aiofauna_llm/schemas/aws_ml.py
aiofauna_llm/schemas/openai.py
aiofauna_llm/schemas/pinecone.py
aiofauna_llm/schemas/typedefs.py
aiofauna_llm/services/__init__.py
aiofauna_llm/services/openai.py
aiofauna_llm/services/pinecone.py
aiofauna_llm/utils.py
aiofauna_llm-0.0.4.dist-info/METADATA
aiofauna_llm-0.0.4.dist-info/WHEEL
aiofauna_llm-0.0.4.dist-info/RECORD
