Metadata-Version: 2.1
Name: aiofauna-llm
Version: 0.0.4
Summary: 
Author: Your Name
Author-email: you@example.com
Requires-Python: >=3.9,<4.0
Classifier: Programming Language :: Python :: 3
Classifier: Programming Language :: Python :: 3.9
Classifier: Programming Language :: Python :: 3.10
Classifier: Programming Language :: Python :: 3.11
Requires-Dist: aiofauna (>=0.1.82,<0.2.0)
Requires-Dist: boto3 (>=1.28.30,<2.0.0)
Requires-Dist: numpy (>=1.25.2,<2.0.0)
Requires-Dist: openai (>=0.27.8,<0.28.0)
Requires-Dist: tiktoken (>=0.4.0,<0.5.0)
